score.es7-0.0.2-py3.7-nspkg.pth
score/es7/__init__.py
score/es7/_init.py
score/es7/ctx.py
score/es7/dsl.py
score.es7-0.0.2.dist-info/COPYING.LESSER.txt
score.es7-0.0.2.dist-info/METADATA
score.es7-0.0.2.dist-info/WHEEL
score.es7-0.0.2.dist-info/namespace_packages.txt
score.es7-0.0.2.dist-info/top_level.txt
score.es7-0.0.2.dist-info/RECORD
