Metadata-Version: 2.1
Name: score.es7
Version: 0.0.2
Summary: ElasticSearch integration for The SCORE Framework
Home-page: http://score-framework.org
Author: strg.at
Author-email: score@strg.at
License: LGPL
Keywords: score framework elasticsearch
Platform: UNKNOWN
Classifier: Development Status :: 4 - Beta
Classifier: Environment :: Console
Classifier: Environment :: Web Environment
Classifier: Framework :: Pyramid
Classifier: Intended Audience :: Developers
Classifier: License :: OSI Approved :: GNU Lesser General Public License v3 or later (LGPLv3+)
Classifier: Operating System :: OS Independent
Classifier: Programming Language :: Python :: 3
Classifier: Programming Language :: Python :: 3.4
Classifier: Topic :: Internet :: WWW/HTTP :: Indexing/Search
Classifier: Topic :: Software Development :: Libraries :: Application Frameworks
Requires-Dist: score.init (>=0.3)
Requires-Dist: elasticsearch (<7.0.0,>=6.0.0)
Requires-Dist: elasticsearch-dsl (<7.0.0,>=6.0.0)
Provides-Extra: dev
Requires-Dist: pytest ; extra == 'dev'
Requires-Dist: score.ctx ; extra == 'dev'
